exness_data_preprocess/__init__.py
exness_data_preprocess/clickhouse_base.py
exness_data_preprocess/clickhouse_client.py
exness_data_preprocess/clickhouse_gap_detector.py
exness_data_preprocess/clickhouse_manager.py
exness_data_preprocess/clickhouse_ohlc_generator.py
exness_data_preprocess/clickhouse_query_engine.py
exness_data_preprocess/config.py
exness_data_preprocess/downloader.py
exness_data_preprocess/exchanges.py
exness_data_preprocess/models.py
exness_data_preprocess/processor.py
exness_data_preprocess/session_detector.py
exness_data_preprocess/tick_loader.py
exness_data_preprocess-2.1.0.dist-info/METADATA
exness_data_preprocess-2.1.0.dist-info/WHEEL
exness_data_preprocess-2.1.0.dist-info/licenses/LICENSE
exness_data_preprocess-2.1.0.dist-info/RECORD
