Metadata-Version: 2.4
Name: exness-data-preprocess
Version: 2.1.0
Summary: Professional Exness forex tick data preprocessing with ClickHouse backend. Provides efficient storage with lossless precision and direct queryability.
Project-URL: Homepage, https://github.com/terrylica/exness-data-preprocess
Project-URL: Documentation, https://github.com/terrylica/exness-data-preprocess#readme
Project-URL: Repository, https://github.com/terrylica/exness-data-preprocess.git
Project-URL: Bug Tracker, https://github.com/terrylica/exness-data-preprocess/issues
Project-URL: Source Code, https://github.com/terrylica/exness-data-preprocess
Project-URL: Changelog, https://github.com/terrylica/exness-data-preprocess/blob/main/CHANGELOG.md
Author-email: Eon Labs <terry@eonlabs.com>
Maintainer-email: Terry Li <terry@eonlabs.com>
License: MIT
License-File: LICENSE
Keywords: backtesting,clickhouse,data-engineering,efficient-storage,eurusd,exness,financial-data,forex,forex-data,lossless,microstructure,ohlc,pandas,preprocessing,quantitative-finance,queryable,tick-data,time-series
Classifier: Development Status :: 3 - Alpha
Classifier: Intended Audience :: Developers
Classifier: Intended Audience :: Financial and Insurance Industry
Classifier: License :: OSI Approved :: MIT License
Classifier: Operating System :: OS Independent
Classifier: Programming Language :: Python :: 3
Classifier: Programming Language :: Python :: 3.11
Classifier: Programming Language :: Python :: 3.12
Classifier: Programming Language :: Python :: 3.13
Classifier: Topic :: Office/Business :: Financial :: Investment
Classifier: Topic :: Scientific/Engineering :: Information Analysis
Classifier: Topic :: Software Development :: Libraries :: Python Modules
Requires-Python: >=3.11
Requires-Dist: clickhouse-connect>=0.7.0
Requires-Dist: exchange-calendars>=4.5.6
Requires-Dist: pandas>=2.0.0
Requires-Dist: pydantic>=2.0.0
Requires-Dist: pyyaml>=6.0.0
Provides-Extra: examples
Requires-Dist: tqdm>=4.65.0; extra == 'examples'
